seadog007_pack/__init__.py
seadog007_pack/seadog007.py
seadog007_pack-1.0.0.dist-info/LICENSE
seadog007_pack-1.0.0.dist-info/METADATA
seadog007_pack-1.0.0.dist-info/WHEEL
seadog007_pack-1.0.0.dist-info/top_level.txt
seadog007_pack-1.0.0.dist-info/RECORD
