Metadata-Version: 2.1
Name: seadog007-pack
Version: 1.0.0
Summary: A example project
Author-email: seadog007 <007seadog@gmail.com>
Project-URL: Homepage, https://seadog007.me
Classifier: Programming Language :: Python :: 3
Classifier: License :: OSI Approved :: MIT License
Classifier: Operating System :: OS Independent
Requires-Python: >=3.7
License-File: LICENSE
